{
	"class" : {
		"modelClass" : "PeterUhnak 8/18/2015 10:29:48" },
	"instance" : {
		"addAsSourceFor:" : "PeterUhnak 8/18/2015 10:29:48",
		"addAsTargetFor:" : "PeterUhnak 8/18/2015 10:29:48",
		"buildEditorForm:" : "PeterUhnak 8/18/2015 10:29:48",
		"canBeSourceFor:" : "PeterUhnak 8/18/2015 10:29:48",
		"canBeTargetFor:" : "PeterUhnak 8/18/2015 10:29:48",
		"diagramController" : "PeterUhnak 8/18/2015 10:29:48",
		"diagramController:" : "PeterUhnak 8/18/2015 10:29:48",
		"figure" : "PeterUhnak 8/18/2015 10:29:48",
		"hideSelectionFeedback" : "PeterUhnak 8/18/2015 10:29:48",
		"layout" : "PeterUhnak 8/18/2015 10:29:48",
		"layout:" : "PeterUhnak 8/18/2015 10:29:48",
		"model" : "PeterUhnak 8/18/2015 10:29:48",
		"model:" : "PeterUhnak 8/18/2015 10:29:48",
		"modelClass" : "PeterUhnak 8/18/2015 10:29:48",
		"parent" : "PeterUhnak 8/18/2015 10:29:48",
		"parent:" : "PeterUhnak 8/18/2015 10:29:48",
		"refreshFigure" : "PeterUhnak 8/18/2015 10:29:48",
		"registerModelEvents:" : "PeterUhnak 9/29/2015 01:06",
		"remove" : "PeterUhnak 8/18/2015 10:29:48",
		"removeModelElement:" : "PeterUhnak 8/18/2015 10:29:48",
		"showSelectionFeedback" : "PeterUhnak 8/18/2015 10:29:48" } }
