{
	"class" : {
		"defaultSpec" : "PeterUhnak 6/28/2016 12:33:32",
		"open" : "PeterUhnak 6/28/2016 12:33:32" },
	"instance" : {
		"cancel" : "PeterUhnak 6/28/2016 12:33:32",
		"chooseFolder" : "PeterUhnak 6/28/2016 12:33:32",
		"initialExtent" : "PeterUhnak 6/28/2016 12:33:32",
		"initialize" : "PeterUhnak 6/28/2016 12:33:32",
		"initializePresenter" : "PeterUhnak 6/28/2016 12:33:32",
		"initializeWidgets" : "PeterUhnak 6/28/2016 12:33:32",
		"open" : "PeterUhnak 6/28/2016 12:33:32",
		"projectController:" : "PeterUhnak 6/28/2016 12:33:32",
		"projectFolderButton" : "PeterUhnak 6/28/2016 12:33:32",
		"projectFolderInput" : "PeterUhnak 6/28/2016 12:33:32",
		"projectFolderLabel" : "PeterUhnak 6/28/2016 12:33:32",
		"projectNameInput" : "PeterUhnak 6/28/2016 12:33:32",
		"projectNameLabel" : "PeterUhnak 6/28/2016 12:33:32",
		"save" : "PeterUhnak 6/28/2016 12:33:32",
		"title" : "PeterUhnak 6/28/2016 12:33:32",
		"updateFolderInput" : "PeterUhnak 6/28/2016 12:33:32" } }
