{
	"class" : {
		"default" : "PeterUhnak 6/3/2016 12:33:06",
		"resetDefault" : "PeterUhnak 6/3/2016 12:33:06",
		"setDefault:" : "PeterUhnak 6/3/2016 12:33:06",
		"withAll" : "PeterUhnak 6/3/2016 12:33:06" },
	"instance" : {
		"add:" : "PeterUhnak 6/3/2016 12:33:06",
		"addAll" : "PeterUhnak 6/3/2016 12:33:06",
		"initialize" : "PeterUhnak 6/3/2016 12:33:06",
		"pluginFor:" : "PeterUhnak 6/3/2016 12:33:06",
		"pluginForController:" : "PeterUhnak 6/3/2016 12:33:06",
		"plugins" : "PeterUhnak 6/3/2016 12:33:06",
		"pluginsDo:" : "PeterUhnak 6/3/2016 12:33:06" } }
