{
	"class" : {
		"fix:nearEndOfEdge:" : "bliznjan 7/20/2015 20:02:27",
		"fix:nearStartOfEdge:" : "bliznjan 7/20/2015 20:02:27",
		"move:nearEndOfEdge:distance:offset:" : "bliznjan 7/20/2015 20:02:27",
		"move:nearStartOfEdge:distance:offset:" : "bliznjan 7/20/2015 20:02:27",
		"stick:nearEndOfEdge:distance:offset:" : "bliznjan 7/20/2015 20:02:27",
		"stick:nearStartOfEdge:distance:offset:" : "bliznjan 7/20/2015 20:02:27" },
	"instance" : {
		"distance:" : "bliznjan 7/20/2015 20:02:27",
		"fix" : "bliznjan 7/20/2015 20:02:27",
		"initialize" : "bliznjan 7/20/2015 20:02:27",
		"move" : "bliznjan 7/20/2015 20:02:27",
		"near" : "bliznjan 7/20/2015 20:02:27",
		"nearEnd" : "bliznjan 7/20/2015 20:02:27",
		"nearStart" : "bliznjan 7/20/2015 20:02:27" } }
