{
	"class" : {
		"defaultSpec" : "PeterUhnak 10/11/2014 18:56",
		"example1" : "PeterUhnak 10/4/2014 14:11",
		"example2" : "PeterUhnak 8/28/2014 22:13",
		"example3" : "PeterUhnak 10/11/2014 19:05",
		"menuCommandOn:" : "bliznjan 10/10/2014 12:39",
		"openFsm" : "PeterUhnak 8/28/2014 21:41",
		"openOn:" : "PeterUhnak 8/28/2014 21:45",
		"openUml" : "PeterUhnak 8/28/2014 21:41",
		"umlite" : "PeterUhnak 8/29/2014 22:30" },
	"instance" : {
		"cancelSelection" : "bliznjan 10/10/2014 10:56",
		"formModel" : "PeterUhnak 7/11/2014 21:49",
		"initialExtent" : "PeterUhnak 7/16/2014 07:47",
		"initializePresenter" : "bliznjan 10/6/2014 14:00",
		"initializeWidgets" : "PeterUhnak 10/4/2014 23:34",
		"open" : "PeterUhnak 7/23/2014 22:32",
		"openDiagram:" : "PeterUhnak 10/6/2014 22:53",
		"openWithSpec" : "PeterUhnak 10/4/2014 23:37",
		"paletteModel" : "PeterUhnak 7/11/2014 21:49",
		"reloadView" : "PeterUhnak 10/6/2014 22:55",
		"roassalModel" : "PeterUhnak 7/11/2014 21:47",
		"selectDelete" : "bliznjan 10/4/2014 19:19",
		"selectEdgeItem:" : "bliznjan 10/4/2014 19:19",
		"selectElementItem:" : "bliznjan 10/4/2014 19:19",
		"selectItem:" : "PeterUhnak 10/6/2014 19:33",
		"statusModel" : "PeterUhnak 7/16/2014 07:43",
		"textEditorModel" : "PeterUhnak 8/16/2014 23:47",
		"title" : "PeterUhnak 7/16/2014 07:43",
		"viewClicked:" : "PeterUhnak 10/6/2014 22:57",
		"viewEdgeClicked:" : "bliznjan 10/10/2014 11:38",
		"viewElementClicked:" : "bliznjan 10/10/2014 11:38" } }
