{
	"class" : {
		 },
	"instance" : {
		"connectionFeedback" : "PeterUhnak 2/12/2016 14:30:20",
		"createEdgeFrom:to:" : "PeterUhnak 2/12/2016 14:30:20",
		"createFigure" : "PeterUhnak 2/12/2016 14:30:20",
		"createModel" : "PeterUhnak 2/12/2016 14:30:20",
		"edgeBuilder" : "PeterUhnak 2/12/2016 14:30:20",
		"layout" : "PeterUhnak 2/12/2016 14:30:20",
		"layout:" : "PeterUhnak 2/12/2016 14:30:20",
		"source" : "PeterUhnak 2/12/2016 14:30:20",
		"source:" : "PeterUhnak 2/12/2016 14:30:20",
		"target:" : "PeterUhnak 2/12/2016 14:30:20" } }
