{
	"class" : {
		"canvas:" : "bliznjan 4/8/2015 12:03:15",
		"example01" : "bliznjan 4/8/2015 12:03:15" },
	"instance" : {
		"applyOversize" : "bliznjan 4/8/2015 12:03:15",
		"asBMP" : "bliznjan 4/8/2015 12:03:15",
		"asGIF" : "bliznjan 4/8/2015 12:03:15",
		"asJPEG" : "bliznjan 4/8/2015 12:03:15",
		"asJPG" : "bliznjan 4/8/2015 12:03:15",
		"asPNG" : "bliznjan 4/8/2015 12:03:15",
		"cameraScale" : "bliznjan 4/8/2015 12:03:15",
		"cameraScale:" : "bliznjan 4/8/2015 12:03:15",
		"canvas:" : "bliznjan 4/8/2015 12:03:15",
		"centered" : "bliznjan 4/8/2015 12:03:15",
		"defaultScale" : "bliznjan 4/8/2015 12:03:15",
		"export" : "bliznjan 4/8/2015 12:03:15",
		"extent" : "bliznjan 4/8/2015 12:03:15",
		"extent:" : "bliznjan 4/8/2015 12:03:15",
		"fileName:" : "bliznjan 4/8/2015 12:03:15",
		"initialize" : "bliznjan 4/8/2015 12:03:15",
		"oversizedBy:" : "bliznjan 4/8/2015 12:03:15",
		"scale:" : "bliznjan 4/8/2015 12:03:15",
		"scaleToMorphLimits" : "bliznjan 4/8/2015 12:03:15",
		"whole" : "bliznjan 4/8/2015 12:03:15",
		"withoutFixedShapes" : "bliznjan 4/8/2015 12:03:15" } }
