{
	"class" : {
		 },
	"instance" : {
		"addLabel:" : "PeterUhnak 4/15/2015 19:22:21",
		"addLabel:text:" : "PeterUhnak 4/15/2015 19:22:21",
		"addLabelsTo:" : "PeterUhnak 4/15/2015 19:22:21",
		"applyConstraintsTo:" : "PeterUhnak 4/15/2015 19:22:21",
		"arrowHead" : "PeterUhnak 4/15/2015 19:22:21",
		"arrowTail" : "PeterUhnak 4/15/2015 19:22:21",
		"attachPoint:" : "PeterUhnak 4/15/2015 19:22:21",
		"circleAttachPoint" : "PeterUhnak 4/15/2015 19:22:21",
		"color:" : "PeterUhnak 4/15/2015 19:22:21",
		"constraintLabel:balance:offset:" : "PeterUhnak 4/15/2015 19:22:21",
		"constraintLabel:below:" : "PeterUhnak 4/15/2015 19:22:21",
		"constraintLabel:onTheRightOf:" : "PeterUhnak 4/15/2015 19:22:21",
		"constraintLabel:toSourceDistance:offset:" : "PeterUhnak 4/15/2015 19:22:21",
		"constraintLabel:toTargetDistance:offset:" : "PeterUhnak 4/15/2015 19:22:21",
		"createEdgeFrom:to:" : "PeterUhnak 4/15/2015 19:22:21",
		"createFigureFrom:to:view:" : "PeterUhnak 4/15/2015 19:22:21",
		"dashDotLine" : "PeterUhnak 4/15/2015 19:22:21",
		"dashedLine" : "PeterUhnak 4/15/2015 19:22:21",
		"defaultColor" : "PeterUhnak 4/15/2015 19:22:21",
		"dottedLine" : "PeterUhnak 4/15/2015 19:22:21",
		"emptyArrowHead" : "PeterUhnak 4/15/2015 19:22:21",
		"emptyArrowTail" : "PeterUhnak 4/15/2015 19:22:21",
		"emptyCircleHead" : "PeterUhnak 4/15/2015 19:22:21",
		"emptyCircleTail" : "PeterUhnak 4/15/2015 19:22:21",
		"emptyDiamondHead" : "PeterUhnak 4/15/2015 19:22:21",
		"emptyDiamondTail" : "PeterUhnak 4/15/2015 19:22:21",
		"emptyNarrowArrowHead" : "PeterUhnak 4/15/2015 19:22:21",
		"emptyNarrowArrowTail" : "PeterUhnak 4/15/2015 19:22:21",
		"filledArrowHead" : "PeterUhnak 4/15/2015 19:22:21",
		"filledArrowTail" : "PeterUhnak 4/15/2015 19:22:21",
		"filledCircleHead" : "PeterUhnak 4/15/2015 19:22:21",
		"filledCircleTail" : "PeterUhnak 4/15/2015 19:22:21",
		"filledDiamondHead" : "PeterUhnak 4/15/2015 19:22:21",
		"filledDiamondTail" : "PeterUhnak 4/15/2015 19:22:21",
		"filledNarrowArrowHead" : "PeterUhnak 4/15/2015 19:22:21",
		"filledNarrowArrowTail" : "PeterUhnak 4/15/2015 19:22:21",
		"head:" : "PeterUhnak 4/15/2015 19:22:21",
		"initialize" : "PeterUhnak 5/1/2015 17:32",
		"labelNamed:" : "PeterUhnak 4/15/2015 19:22:21",
		"line" : "PeterUhnak 5/1/2015 17:33",
		"lineWidth:" : "PeterUhnak 4/15/2015 19:22:21",
		"multiLine" : "PeterUhnak 5/1/2015 17:36",
		"newLabel" : "PeterUhnak 4/15/2015 19:22:21",
		"newLabel:" : "PeterUhnak 4/15/2015 19:22:21",
		"noHead" : "PeterUhnak 4/15/2015 19:22:21",
		"noTail" : "PeterUhnak 4/15/2015 19:22:21",
		"notDecorated" : "PeterUhnak 4/15/2015 19:22:21",
		"rectangleAttachPoint" : "PeterUhnak 4/15/2015 19:22:21",
		"solidLine" : "PeterUhnak 4/15/2015 19:22:21",
		"tail:" : "PeterUhnak 4/15/2015 19:22:21",
		"updateLabel:whenChanged:" : "PeterUhnak 4/15/2015 19:22:21" } }
