{
	"class" : {
		 },
	"instance" : {
		"setUp" : "PeterUhnak 7/23/2015 22:02:58",
		"tearDown" : "PeterUhnak 7/23/2015 22:02:58",
		"testAccessors" : "PeterUhnak 7/23/2015 22:02:58",
		"testAddingAndRemoving" : "PeterUhnak 7/23/2015 22:02:58",
		"testElementsTranslation" : "PeterUhnak 7/23/2015 22:02:58",
		"testFixedPosition" : "PeterUhnak 7/23/2015 22:02:58",
		"testMultipleElements" : "PeterUhnak 7/23/2015 22:02:58",
		"testSourcesOnly" : "PeterUhnak 7/23/2015 22:02:58",
		"testStraightLine" : "PeterUhnak 7/23/2015 22:02:58",
		"testTargetsOnly" : "PeterUhnak 7/23/2015 22:02:58" } }
