{
	"class" : {
		"current" : "PeterUhnak 6/18/2015 07:14:09" },
	"instance" : {
		"dcFsmDiagramIcon" : "PeterUhnak 6/18/2015 07:14:09",
		"dcFsmDiagramIconContents" : "PeterUhnak 6/18/2015 07:14:09",
		"dcFsmFinalStateIcon" : "PeterUhnak 6/18/2015 07:14:09",
		"dcFsmFinalStateIconContents" : "PeterUhnak 6/18/2015 07:14:09",
		"dcFsmInitialStateIcon" : "PeterUhnak 6/18/2015 07:14:09",
		"dcFsmInitialStateIconContents" : "PeterUhnak 6/18/2015 07:14:09",
		"dcFsmRegularStateIcon" : "PeterUhnak 6/18/2015 07:14:09",
		"dcFsmRegularStateIconContents" : "PeterUhnak 6/18/2015 07:14:09",
		"dcFsmTransitionIcon" : "PeterUhnak 6/18/2015 07:14:09",
		"dcFsmTransitionIconContents" : "PeterUhnak 6/18/2015 07:14:09",
		"dcOmlBoxIcon" : "PeterUhnak 6/18/2015 07:14:09",
		"dcOmlBoxIconContents" : "PeterUhnak 6/18/2015 07:14:09",
		"dcOmlDiagramIcon" : "PeterUhnak 6/18/2015 07:14:09",
		"dcOmlDiagramIconContents" : "PeterUhnak 6/18/2015 07:14:09",
		"dcSelectIcon" : "PeterUhnak 6/18/2015 07:14:09",
		"dcSelectIconContents" : "PeterUhnak 6/18/2015 07:14:09",
		"dynacaseIcon" : "PeterUhnak 6/18/2015 07:14:09",
		"dynacaseIconContents" : "PeterUhnak 6/18/2015 07:14:09",
		"gtInspectorIconsIn:" : "PeterUhnak 6/18/2015 07:14:09",
		"iconSelectors" : "PeterUhnak 6/18/2015 07:14:09",
		"initialize" : "PeterUhnak 6/18/2015 07:14:09",
		"initializeIcons" : "PeterUhnak 6/18/2015 07:14:09" } }
