{
	"class" : {
		 },
	"instance" : {
		"addDiagramController:" : "PeterUhnak 4/2/2015 08:28:24",
		"initialize" : "PeterUhnak 4/2/2015 08:28:24",
		"layoutFor:" : "PeterUhnak 4/2/2015 08:28:24",
		"openFirstDiagram" : "PeterUhnak 4/2/2015 08:28:24",
		"persistLayouts" : "PeterUhnak 4/2/2015 08:28:24",
		"project" : "PeterUhnak 4/2/2015 08:28:24",
		"project:" : "PeterUhnak 4/2/2015 08:28:24",
		"removeDiagramController:" : "PeterUhnak 4/2/2015 08:28:24",
		"workbench:" : "PeterUhnak 4/2/2015 08:28:24" } }
