{
	"class" : {
		"defaultSpec" : "PeterUhnak 3/1/2016 13:35:17",
		"openOn:" : "PeterUhnak 3/1/2016 13:35:17" },
	"instance" : {
		"childrenFor:" : "PeterUhnak 3/1/2016 13:35:17",
		"deleteDiagramCommand:" : "PeterUhnak 3/1/2016 13:35:17",
		"deleteElementCommand:" : "PeterUhnak 3/1/2016 13:35:17",
		"displayFor:" : "PeterUhnak 3/1/2016 13:35:17",
		"doubleClick" : "PeterUhnak 3/1/2016 13:35:17",
		"editElementCommand:" : "PeterUhnak 3/1/2016 13:35:17",
		"iconFor:" : "PeterUhnak 3/1/2016 13:35:17",
		"initialize" : "PeterUhnak 3/1/2016 13:35:17",
		"initializeTree" : "PeterUhnak 3/1/2016 13:35:17",
		"initializeWidgets" : "PeterUhnak 3/1/2016 13:35:17",
		"inspectCommand:" : "PeterUhnak 3/1/2016 13:35:17",
		"openCommand:" : "PeterUhnak 3/1/2016 13:35:17",
		"openOn:" : "PeterUhnak 3/1/2016 13:35:17",
		"registerAdapter:" : "PeterUhnak 3/1/2016 13:35:17",
		"registerAdapters" : "PeterUhnak 3/1/2016 13:35:17",
		"renameCommand:" : "PeterUhnak 3/1/2016 13:35:17",
		"rightClickMenu:" : "PeterUhnak 3/1/2016 13:35:17",
		"tree" : "PeterUhnak 3/1/2016 13:35:17",
		"workbench" : "PeterUhnak 3/1/2016 13:35:17" } }
